skytraq-0.0.1.dist-info/metadata.json
skytraq-0.0.1.dist-info/DESCRIPTION.rst
skytraq-0.0.1.dist-info/RECORD
skytraq-0.0.1.dist-info/WHEEL
skytraq-0.0.1.dist-info/METADATA
skytraq-0.0.1.dist-info/top_level.txt
skytraq/__init__.py
skytraq/venus6.py
