Metadata-Version: 2.0
Name: skytraq
Version: 0.0.1
Summary: SkyTraq GPS binary protocal implementation
Home-page: https://github.com/r0ro/skytraq
Author: r0ro
Author-email: r0ro@free.fr
License: MIT
Keywords: gps skytraq venus venus6 photo tagger
Platform: UNKNOWN
Classifier: Development Status :: 3 - Alpha
Classifier: License :: OSI Approved :: MIT License
Classifier: Programming Language :: Python :: 3.4
Requires-Dist: pyserial
